ghcontribs/__init__.py
ghcontribs/_installed_version.py
ghcontribs/_version.py
ghcontribs/contrib.py
ghcontribs/get_contribs.py
ghcontribs/json_utils.py
ghcontribs/monthly.py
ghcontribs/query.py
ghcontribs/version.py
ghcontribs/tests/__init__.py
ghcontribs/tests/conftest.py
ghcontribs/tests/test_contrib.py
ghcontribs/tests/test_get_contribs.py
ghcontribs/tests/test_json_utils.py
ghcontribs/tests/test_monthly.py
ghcontribs/tests/test_query.py
ghcontribs/tests/utils.py
ghcontribs-0.0.1.dist-info/LICENSE
ghcontribs-0.0.1.dist-info/METADATA
ghcontribs-0.0.1.dist-info/WHEEL
ghcontribs-0.0.1.dist-info/top_level.txt
ghcontribs-0.0.1.dist-info/RECORD
